ectp-6.3.12.data/data/thostmduserapi.dll
ectp-6.3.12.data/data/thosttraderapi.dll
ptp/Algos.py
ptp/CythonLib.cp36-win_amd64.pyd
ptp/CythonLib.py
ptp/MdApi.cp36-win_amd64.pyd
ptp/TraderApi.cp36-win_amd64.pyd
ptp/__init__.py
ptp/py_ApiStructure.py
ptp/py_CtpMd.py
ptp/py_CtpTrader.py
ptp/py_base.py
pymysql/CLIENT.py
pymysql/COMMAND.py
pymysql/CR.py
pymysql/ER.py
pymysql/FIELD_TYPE.py
pymysql/FLAG.py
pymysql/SERVER_STATUS.py
pymysql/__init__.py
pymysql/_auth.py
pymysql/_compat.py
pymysql/_socketio.py
pymysql/charset.py
pymysql/connections.py
pymysql/converters.py
pymysql/cursors.py
pymysql/err.py
pymysql/optionfile.py
pymysql/protocol.py
pymysql/times.py
pymysql/util.py
ectp-6.3.12.dist-info/METADATA
ectp-6.3.12.dist-info/WHEEL
ectp-6.3.12.dist-info/entry_points.txt
ectp-6.3.12.dist-info/top_level.txt
ectp-6.3.12.dist-info/RECORD
